setup.py
mess_server_test_Ensueno.egg-info/PKG-INFO
mess_server_test_Ensueno.egg-info/SOURCES.txt
mess_server_test_Ensueno.egg-info/dependency_links.txt
mess_server_test_Ensueno.egg-info/requires.txt
mess_server_test_Ensueno.egg-info/top_level.txt
server/__init__.py
server/server_script.py
server/setup_server.py
server/common/__init__.py
server/common/decorators.py
server/common/descriptors.py
server/common/errors.py
server/common/metaclasses.py
server/common/parent_classfile.py
server/common/vars.py
server/docs/__init__.py
server/docs/conf.py
server/project_logging/__init__.py
server/project_logging/configs/__init__.py
server/project_logging/configs/client_log_config.py
server/project_logging/configs/server_log_config.py
server/project_logging/log/__init__.py
server/server/__init__.py
server/server/server_classfile.py
server/server/db/__init__.py
server/server/db/server_db.py
server/server/gui/__init__.py
server/server/gui/register_client.py
server/server/gui/remove_client.py
server/server/gui/server_gui.py
server/server/gui/server_window.py