Metadata-Version: 2.1
Name: mess-server-test-Ensueno
Version: 0.8.7
Summary: mess_server
Home-page: UNKNOWN
Author: Ensueno
Author-email: inspiracion@yandex.ru
License: UNKNOWN
Platform: UNKNOWN
